modihub/__init__.py
modihub/eval/__init__.py
modihub/eval/evaluator.py
modihub/llm/__init__.py
modihub/llm/anthropi_client.py
modihub/llm/base.py
modihub/llm/gemini_client.py
modihub/llm/groq_client.py
modihub/llm/llm.py
modihub/llm/ollama_client.py
modihub/llm/openai_client.py
modihub/metrics/__init__.py
modihub/metrics/metrics.py
modihub/utils/__init__.py
modihub/utils/image_utils.py
modihub-1.0.2.dist-info/METADATA
modihub-1.0.2.dist-info/WHEEL
modihub-1.0.2.dist-info/RECORD
