Metadata-Version: 2.4
Name: modihub
Version: 1.0.2
Summary: A Unified Interface for Diverse LLMs
Author-email: haruiz <henryruiz22@gmail.com>
Requires-Python: >=3.10
Requires-Dist: anthropic>=0.49.0
Requires-Dist: google-genai>=1.7.0
Requires-Dist: groq>=0.20.0
Requires-Dist: nltk>=3.9.1
Requires-Dist: ollama>=0.3.3
Requires-Dist: openai>=1.68.2
Requires-Dist: pillow>=11.0.0
Requires-Dist: pydantic>=2.9.2
Requires-Dist: python-dotenv>=1.0.1
Requires-Dist: tenacity>=9.0.0
